aws_priviledge_deescalation/__init__.py
aws_priviledge_deescalation/priviledge_deescalation.py
bapp_aws_priviledge_deescalation-0.0.1.dist-info/LICENSE
bapp_aws_priviledge_deescalation-0.0.1.dist-info/WHEEL
bapp_aws_priviledge_deescalation-0.0.1.dist-info/METADATA
bapp_aws_priviledge_deescalation-0.0.1.dist-info/RECORD
