Metadata-Version: 2.1
Name: bapp-aws-priviledge-deescalation
Version: 0.0.1
Summary: balcony app for preventing IAM Role & User priviledge escalation by creating customized IAM Permission Boundaries for each of them 
License: Apache-2
Author: Oguzhan Yilmaz
Author-email: oguzhanylmz271@gmail.com
Requires-Python: >=3.7,<4.0
Classifier: License :: Other/Proprietary License
Classifier: Programming Language :: Python :: 3
Classifier: Programming Language :: Python :: 3.7
Classifier: Programming Language :: Python :: 3.8
Classifier: Programming Language :: Python :: 3.9
Classifier: Programming Language :: Python :: 3.10
